README.md
setup.py
.idea/.gitignore
.idea/bblt.iml
.idea/misc.xml
.idea/modules.xml
.idea/vcs.xml
.idea/inspectionProfiles/Project_Default.xml
.idea/inspectionProfiles/profiles_settings.xml
bblt/__init__.py
bblt/appium_driver.py
bblt/launchtime.py
bblt/line.py
bblt/ocr_util.py
bblt/requirements.txt
bblt/settings.ini
bblt/test.py
bblt.egg-info/PKG-INFO
bblt.egg-info/SOURCES.txt
bblt.egg-info/dependency_links.txt
bblt.egg-info/requires.txt
bblt.egg-info/top_level.txt
bblt/__pycache__/__init__.cpython-39.pyc
bblt/__pycache__/appium_driver.cpython-39.pyc
bblt/__pycache__/launchtime.cpython-39.pyc
bblt/__pycache__/ocr_util.cpython-39.pyc
dist/bblt-25.4.17.1.tar.gz