Metadata-Version: 1.0
Name: bblt
Version: 26.1.5.1
Summary: APP Launch Test
Home-page: https://github.com/xiaoyaoamiao/lt.git
Author: bob
Author-email: miao2005xu@163.com
License: MIT License
Keywords: launchtest
Platform: any
